[
  {
    "header": "Active Nets"
  },
  {
    "name": "EagleNet",
    "description": "West Central Florida Daily NTS Net on NI4CE"
  },
  {
    "name": "EagleNet",
    "description": "West Central Florida Daily NTS Net on NI4CE"
  },
  {
    "name": "EagleNet",
    "description": "West Central Florida Daily NTS Net on NI4CE"
  },
  {
    "header": "Completed Nets"
  },
  {
    "name": "EagleNet",
    "description": "West Central Florida Daily NTS Net on NI4CE"
  },
  {
    "name": "EagleNet",
    "description": "West Central Florida Daily NTS Net on NI4CE"
  },
  {
    "name": "EagleNet",
    "description": "West Central Florida Daily NTS Net on NI4CE"
  }
]
